iamra/__init__.py
iamra/exceptions.py
iamra/py.typed
iamra/session.py
iamra-0.6.0.dist-info/METADATA
iamra-0.6.0.dist-info/WHEEL
iamra-0.6.0.dist-info/LICENSE
iamra-0.6.0.dist-info/RECORD
