Metadata-Version: 2.1
Name: iamra
Version: 0.6.0
Summary: IAM Roles Anywhere credentials helper
Home-page: https://github.com/gadams999/iamra
License: MIT
Author: Gavin Adams
Author-email: me@gavinadams.org
Requires-Python: >=3.9,<4.0
Classifier: Development Status :: 1 - Planning
Classifier: License :: OSI Approved :: MIT License
Classifier: Programming Language :: Python :: 3
Classifier: Programming Language :: Python :: 3.9
Classifier: Programming Language :: Python :: 3.10
Classifier: Programming Language :: Python :: 3.11
Requires-Dist: boto3 (>=1.26.50,<2.0.0)
Requires-Dist: cryptography (>=39.0.0,<40.0.0)
Requires-Dist: requests (>=2.28.1,<3.0.0)
Requires-Dist: urllib3 (>=1.26.13,<2.0.0)
Project-URL: Changelog, https://github.com/gadams999/iamra/releases
Project-URL: Documentation, https://iamra.readthedocs.io
Project-URL: Repository, https://github.com/gadams999/iamra
